{
  "routes": [
    {
      "method": "GET",
      "path": "/papers",
      "handler": "paper.find",
      "config": {
        "policies": []
      }
    },
    {
      "method": "GET",
      "path": "/papers/count",
      "handler": "paper.count",
      "config": {
        "policies": []
      }
    },
    {
      "method": "GET",
      "path": "/papers/:id",
      "handler": "paper.findOne",
      "config": {
        "policies": []
      }
    },
    {
      "method": "POST",
      "path": "/papers",
      "handler": "paper.create",
      "config": {
        "policies": []
      }
    },
    {
      "method": "PUT",
      "path": "/papers/:id",
      "handler": "paper.update",
      "config": {
        "policies": []
      }
    },
    {
      "method": "DELETE",
      "path": "/papers/:id",
      "handler": "paper.delete",
      "config": {
        "policies": []
      }
    }
  ]
}
